mikado_graph/__init__.py
mikado_graph/mikado_graph.py
mikado_graph-0.1.5.dist-info/METADATA
mikado_graph-0.1.5.dist-info/RECORD
mikado_graph-0.1.5.dist-info/WHEEL
mikado_graph-0.1.5.dist-info/entry_points.txt
mikado_graph-0.1.5.dist-info/top_level.txt
