Metadata-Version: 2.1
Name: mikado-graph
Version: 0.1.5
Summary: Python tool to draw graphs for Mikado refactoring
Home-page: https://github.com/syrianspock/mikado-graph
Author: Salah Missri
Author-email: syrianspock@gmail.com
License: UNKNOWN
Platform: UNKNOWN
Classifier: Programming Language :: Python :: 3
Classifier: License :: OSI Approved :: MIT License
Classifier: Operating System :: OS Independent
Requires-Dist: graphviz
Requires-Dist: watchdog
